deldenoiser/__init__.py
deldenoiser/conftest.py
deldenoiser/nullblockmodel.py
deldenoiser/pbs_algorithm.py
deldenoiser/tests/__init__.py
deldenoiser/tests/test_deldenoiser.py
deldenoiser-2.0.0.data/scripts/deldenoiser
deldenoiser-2.0.0.dist-info/LICENSE
deldenoiser-2.0.0.dist-info/METADATA
deldenoiser-2.0.0.dist-info/WHEEL
deldenoiser-2.0.0.dist-info/top_level.txt
deldenoiser-2.0.0.dist-info/RECORD
