Metadata-Version: 2.1
Name: deldenoiser
Version: 2.0.0
Summary: Denoise sequencing data from DEL screens.
Home-page: https://github.com/totient-bio/deldenoiser
Author: Peter Komar
Author-email: peter.komar@totient.bio
Maintainer: Peter Komar
Maintainer-email: peter.komar@totient.bio
License: Copyright (c) 2020 Totient, Inc.
Platform: UNKNOWN
Classifier: Programming Language :: Python :: 3
Classifier: License :: OSI Approved :: GNU General Public License v3 (GPLv3)
Classifier: Operating System :: POSIX
Requires-Python: >=3.6
Requires-Dist: numpy
Requires-Dist: scipy
Requires-Dist: pandas
